common/utils.py
pmd/__init__.py
pmd/_load.py
pmd/cli.py
pmd/load.py
pmd/placeholders.py
pmd/render.py
ymd/__init__.py
ymd/cli.py
ymd/file.py
ymd/load.py
ymd/models.py
ymd/render.py
ymd_prompt-0.3.0.dist-info/licenses/LICENSE
ymd_prompt-0.3.0.dist-info/METADATA
ymd_prompt-0.3.0.dist-info/WHEEL
ymd_prompt-0.3.0.dist-info/entry_points.txt
ymd_prompt-0.3.0.dist-info/top_level.txt
ymd_prompt-0.3.0.dist-info/RECORD
