Metadata-Version: 2.4
Name: ymd-prompt
Version: 0.3.0
Summary: Load, validate, and render YMD (YAML + Markdown) prompt files with Pydantic + Jinja2.
Author-email: Davi Guides <davi.guides@gmail.com>
License-Expression: MIT
Project-URL: Homepage, https://github.com/daviguides/ymd-prompt
Project-URL: Repository, https://github.com/daviguides/ymd-prompt
Project-URL: Issues, https://github.com/daviguides/ymd-prompt/issues
Keywords: prompt,yaml,markdown,ymd,jinja2,llm
Classifier: Programming Language :: Python :: 3
Classifier: Intended Audience :: Developers
Classifier: Topic :: Software Development :: Libraries
Requires-Python: >=3.11
License-File: LICENSE
Requires-Dist: pydantic>=2.6
Requires-Dist: pyyaml>=6.0.1
Requires-Dist: jinja2>=3.1.3
Requires-Dist: typer>=0.17.4
Dynamic: license-file
